README.md
setup.py
epytech/login.py
epytech/notif.py
epytech/session.py
epytech/user.py
epytech.egg-info/PKG-INFO
epytech.egg-info/SOURCES.txt
epytech.egg-info/dependency_links.txt
epytech.egg-info/top_level.txt