Metadata-Version: 2.1
Name: epytech
Version: 0.9
Summary: The python's api for epitech's intra
Home-page: https://github.com/Neotoxic-off/epytch
Author: Neo
Author-email: paul.gardien@epitech.eu
License: MIT
Platform: UNKNOWN
Requires-Python: >= 3.4
